image_poetry/__init__.py
image_poetry/cli.py
image_poetry/generator.py
image_to_poetry-0.0.1.dist-info/METADATA
image_to_poetry-0.0.1.dist-info/WHEEL
image_to_poetry-0.0.1.dist-info/entry_points.txt
image_to_poetry-0.0.1.dist-info/licenses/LICENSE
image_to_poetry-0.0.1.dist-info/RECORD
